promstats/__init__.py
promstats/_async.py
promstats/_timer.py
promstats/_util.py
promstats-0.1.4.dist-info/DESCRIPTION.rst
promstats-0.1.4.dist-info/METADATA
promstats-0.1.4.dist-info/RECORD
promstats-0.1.4.dist-info/WHEEL
promstats-0.1.4.dist-info/metadata.json
promstats-0.1.4.dist-info/top_level.txt
