Metadata-Version: 2.0
Name: promstats
Version: 0.1.4
Summary: syntax sugar for Prometheus client.
Home-page: https://github.com/Intel471/prom-stats/
Author: Intel 471
Author-email: dev@intel471.com
License: MIT
Platform: UNKNOWN
Classifier: License :: OSI Approved :: MIT License
Classifier: Intended Audience :: Developers
Classifier: Programming Language :: Python
Classifier: Programming Language :: Python :: 2
Classifier: Programming Language :: Python :: 2.7
Classifier: Programming Language :: Python :: 3
Classifier: Programming Language :: Python :: 3.4
Classifier: Programming Language :: Python :: 3.5
Classifier: Programming Language :: Python :: 3.6
Classifier: Development Status :: 4 - Beta
Classifier: Operating System :: POSIX
Classifier: Topic :: System :: Monitoring
Requires-Dist: prometheus-client (>=0.0.19)
